tarsier/__init__.py
tarsier/__main__.py
tarsier/_utils.py
tarsier/adapter/__init__.py
tarsier/adapter/_base.py
tarsier/adapter/playwright.py
tarsier/adapter/selenium.py
tarsier/adapter/types.py
tarsier/core.py
tarsier/ocr/__init__.py
tarsier/ocr/ocr_service.py
tarsier/ocr/types.py
tarsier/py.typed
tarsier/tag_utils.min.js
tarsier/text_format.py
tarsier-0.8.2.dist-info/LICENSE
tarsier-0.8.2.dist-info/METADATA
tarsier-0.8.2.dist-info/WHEEL
tarsier-0.8.2.dist-info/RECORD
