Metadata-Version: 2.1
Name: tarsier
Version: 0.8.2
Summary: Vision utilities for web interaction agents
Author: Rohan Pandey
Requires-Python: >=3.11,<4.0
Classifier: Programming Language :: Python :: 3
Classifier: Programming Language :: Python :: 3.11
Classifier: Programming Language :: Python :: 3.12
Requires-Dist: azure-ai-vision-imageanalysis (>=1.0.0b2,<2.0.0)
Requires-Dist: google-cloud-vision (>=3.7.2,<4.0.0)
Requires-Dist: playwright (>=1.44.0,<2.0.0)
Requires-Dist: selenium (>=4.21.0,<5.0.0)
